pyappscan/__init__.py
pyappscan/__packageinfo__.py
pyappscan/exceptions.py
pyappscan/helper.py
pyappscan/pyappscan.py
pyappscan/query.py
pyappscan-1.0.2.dist-info/LICENSE
pyappscan-1.0.2.dist-info/METADATA
pyappscan-1.0.2.dist-info/WHEEL
pyappscan-1.0.2.dist-info/top_level.txt
pyappscan-1.0.2.dist-info/RECORD
