Metadata-Version: 2.1
Name: pyappscan
Version: 1.0.2
Summary: Python REST API Wrapper for IBM/HCL Appscan, a tool which helps scan and report on website and mobile app vulnerabilities.
Home-page: https://github.com/arcsector/pyappscan
Author: arcsector
Author-email: pyappscan.6elf0@slmail.me
Requires-Python: >=3.5.0
License-File: LICENSE
Requires-Dist: requests (>=2.22.0)
Requires-Dist: beautifulsoup4 (>=4.0.0)
